[{"data":{"channelNo":"GOV-QWY-C","channelName":"秦务员APP","brandLogo":"https://mdn.alipayobjects.com/merchant_appfe/afts/img/A*YCyKSLKfTuwAAAAAAAAAAAAADiR2AQ/original","brandMainIMG":"https://mdn.alipayobjects.com/merchant_appfe/afts/img/A*iSp3S7_xWusAAAAAAAAAAAAADiR2AQ/original","brandBlessText":"秦务员祝你虎年大吉","startTime":1642521600000,"endTime":1643637540000,"processIMG":"https://gw.alipayobjects.com/mdn/rms_c75999/afts/img/A*dpVrR7WYt-YAAAAAAAAAAAAAARQnAQ","activityIMG":"https://mdn.alipayobjects.com/merchant_appfe/afts/img/A*omOYQKK59KYAAAAAAAAAAAAADiR2AQ/os","beforeActivity":{"title":"活动暂未开始","subtitle":"请在1月19日后来参加"},"afterActivity":{"title":"活动已结束","subtitle":"恭祝新春大吉"}},"config":{"style":{},"plugin":{"@alipay/peiqi-plugin-box":{}}},"uid":"c81c8dcc0601f11ec97f03b3af9849aeb","name":"@alipay/preheat-2022"}]